setup.py
bunny1.egg-info/PKG-INFO
bunny1.egg-info/SOURCES.txt
bunny1.egg-info/dependency_links.txt
bunny1.egg-info/requires.txt
bunny1.egg-info/top_level.txt
src/__init__.py
src/b1_barebones.py
src/b1_example.py
src/bunny1.py