Metadata-Version: 1.0
Name: bunny1
Version: 1.1
Summary: bunny1 is a tool that lets you write smart bookmarks in python and then share them across all your browsers and with a group of people or the whole world.
Home-page: http://www.bunny1.org/
Author: facebook
Author-email: bunny1-feedback@lists.facebook.com
License: UNKNOWN
Platform: UNKNOWN
